{
  "externalControllerServices" : {
    "78e6b768-aeb8-3b84-8046-96f83cf31033" : {
      "identifier" : "78e6b768-aeb8-3b84-8046-96f83cf31033",
      "name" : "CSVRecordSetWriter"
    },
    "f8fe6515-589a-36d7-9cdd-2c3cd1bb0209" : {
      "identifier" : "f8fe6515-589a-36d7-9cdd-2c3cd1bb0209",
      "name" : "DBCPConnectionPool"
    }
  },
  "flow" : {
    "createdTimestamp" : 1784021319752,
    "description" : "",
    "identifier" : "database-upload",
    "lastModifiedTimestamp" : 1784021319752,
    "name" : "database-upload",
    "versionCount" : 0
  },
  "flowContents" : {
    "comments" : "",
    "componentType" : "PROCESS_GROUP",
    "connections" : [ {
      "backPressureDataSizeThreshold" : "1 GB",
      "backPressureObjectThreshold" : 10000,
      "bends" : [ ],
      "componentType" : "CONNECTION",
      "destination" : {
        "comments" : "",
        "groupId" : "flow-contents-group",
        "id" : "52dd80d1-045a-3bbc-ae35-9275fcbfa4c7",
        "name" : "CreateInsertStatement",
        "type" : "PROCESSOR"
      },
      "flowFileExpiration" : "0 sec",
      "groupIdentifier" : "flow-contents-group",
      "identifier" : "0ad55c4f-c03d-3125-a1e7-7dae2bf5c25f",
      "labelIndex" : 1,
      "loadBalanceCompression" : "DO_NOT_COMPRESS",
      "loadBalanceStrategy" : "DO_NOT_LOAD_BALANCE",
      "name" : "",
      "prioritizers" : [ ],
      "selectedRelationships" : [ "Response" ],
      "source" : {
        "comments" : "",
        "groupId" : "flow-contents-group",
        "id" : "36681431-afa3-3fab-9477-d7f2a18272dd",
        "name" : "PostToUploadAPI",
        "type" : "PROCESSOR"
      },
      "zIndex" : 0
    }, {
      "backPressureDataSizeThreshold" : "1 GB",
      "backPressureObjectThreshold" : 10000,
      "bends" : [ ],
      "componentType" : "CONNECTION",
      "destination" : {
        "comments" : "",
        "groupId" : "flow-contents-group",
        "id" : "36681431-afa3-3fab-9477-d7f2a18272dd",
        "name" : "PostToUploadAPI",
        "type" : "PROCESSOR"
      },
      "flowFileExpiration" : "0 sec",
      "groupIdentifier" : "flow-contents-group",
      "identifier" : "12034d7f-aa97-3df9-bc42-4a7795655908",
      "labelIndex" : 1,
      "loadBalanceCompression" : "DO_NOT_COMPRESS",
      "loadBalanceStrategy" : "DO_NOT_LOAD_BALANCE",
      "name" : "",
      "prioritizers" : [ ],
      "selectedRelationships" : [ "success" ],
      "source" : {
        "comments" : "",
        "groupId" : "flow-contents-group",
        "id" : "11c59787-b8ee-3c3e-92c2-948057eddcd4",
        "name" : "PathForSalesReturn",
        "type" : "PROCESSOR"
      },
      "zIndex" : 0
    }, {
      "backPressureDataSizeThreshold" : "1 GB",
      "backPressureObjectThreshold" : 10000,
      "bends" : [ ],
      "componentType" : "CONNECTION",
      "destination" : {
        "comments" : "",
        "groupId" : "flow-contents-group",
        "id" : "36681431-afa3-3fab-9477-d7f2a18272dd",
        "name" : "PostToUploadAPI",
        "type" : "PROCESSOR"
      },
      "flowFileExpiration" : "0 sec",
      "groupIdentifier" : "flow-contents-group",
      "identifier" : "14691afa-ca35-3b98-b5d8-22667cd29d91",
      "labelIndex" : 1,
      "loadBalanceCompression" : "DO_NOT_COMPRESS",
      "loadBalanceStrategy" : "DO_NOT_LOAD_BALANCE",
      "name" : "",
      "prioritizers" : [ ],
      "selectedRelationships" : [ "success" ],
      "source" : {
        "comments" : "",
        "groupId" : "flow-contents-group",
        "id" : "36d95e6e-9bc1-340f-9309-3ac5ce73e17b",
        "name" : "PathForCustomer",
        "type" : "PROCESSOR"
      },
      "zIndex" : 0
    }, {
      "backPressureDataSizeThreshold" : "1 GB",
      "backPressureObjectThreshold" : 10000,
      "bends" : [ ],
      "componentType" : "CONNECTION",
      "destination" : {
        "comments" : "",
        "groupId" : "flow-contents-group",
        "id" : "36681431-afa3-3fab-9477-d7f2a18272dd",
        "name" : "PostToUploadAPI",
        "type" : "PROCESSOR"
      },
      "flowFileExpiration" : "0 sec",
      "groupIdentifier" : "flow-contents-group",
      "identifier" : "314d9131-a4f0-30af-93fa-78a14e3c0ad6",
      "labelIndex" : 1,
      "loadBalanceCompression" : "DO_NOT_COMPRESS",
      "loadBalanceStrategy" : "DO_NOT_LOAD_BALANCE",
      "name" : "",
      "prioritizers" : [ ],
      "selectedRelationships" : [ "success" ],
      "source" : {
        "comments" : "",
        "groupId" : "flow-contents-group",
        "id" : "f20cd14c-f020-3783-b947-38ea397c6db8",
        "name" : "PathForSales",
        "type" : "PROCESSOR"
      },
      "zIndex" : 0
    }, {
      "backPressureDataSizeThreshold" : "1 GB",
      "backPressureObjectThreshold" : 10000,
      "bends" : [ ],
      "componentType" : "CONNECTION",
      "destination" : {
        "comments" : "",
        "groupId" : "flow-contents-group",
        "id" : "663e7d81-8ec8-3da7-84bd-c949b112cef7",
        "name" : "LogToSyncTracking",
        "type" : "PROCESSOR"
      },
      "flowFileExpiration" : "0 sec",
      "groupIdentifier" : "flow-contents-group",
      "identifier" : "3bc7fdf9-d08e-3756-a92d-7b3ebfa8baf0",
      "labelIndex" : 1,
      "loadBalanceCompression" : "DO_NOT_COMPRESS",
      "loadBalanceStrategy" : "DO_NOT_LOAD_BALANCE",
      "name" : "",
      "prioritizers" : [ ],
      "selectedRelationships" : [ "success" ],
      "source" : {
        "comments" : "",
        "groupId" : "flow-contents-group",
        "id" : "52dd80d1-045a-3bbc-ae35-9275fcbfa4c7",
        "name" : "CreateInsertStatement",
        "type" : "PROCESSOR"
      },
      "zIndex" : 0
    }, {
      "backPressureDataSizeThreshold" : "1 GB",
      "backPressureObjectThreshold" : 10000,
      "bends" : [ ],
      "componentType" : "CONNECTION",
      "destination" : {
        "comments" : "",
        "groupId" : "flow-contents-group",
        "id" : "36681431-afa3-3fab-9477-d7f2a18272dd",
        "name" : "PostToUploadAPI",
        "type" : "PROCESSOR"
      },
      "flowFileExpiration" : "0 sec",
      "groupIdentifier" : "flow-contents-group",
      "identifier" : "51c79310-c610-3440-8568-edf8e92d6587",
      "labelIndex" : 1,
      "loadBalanceCompression" : "DO_NOT_COMPRESS",
      "loadBalanceStrategy" : "DO_NOT_LOAD_BALANCE",
      "name" : "",
      "prioritizers" : [ ],
      "selectedRelationships" : [ "success" ],
      "source" : {
        "comments" : "",
        "groupId" : "flow-contents-group",
        "id" : "cece8839-87f4-3fd3-a650-1a05558d21d0",
        "name" : "PathForProduct",
        "type" : "PROCESSOR"
      },
      "zIndex" : 0
    }, {
      "backPressureDataSizeThreshold" : "1 GB",
      "backPressureObjectThreshold" : 10000,
      "bends" : [ ],
      "componentType" : "CONNECTION",
      "destination" : {
        "groupId" : "flow-contents-group",
        "id" : "31612479-f8a9-3976-a7c9-80c634c046ff",
        "name" : "db-upload-error-out",
        "type" : "OUTPUT_PORT"
      },
      "flowFileExpiration" : "0 sec",
      "groupIdentifier" : "flow-contents-group",
      "identifier" : "61bfcd6b-a662-342c-bbc5-b7aa6f4e5d6a",
      "labelIndex" : 1,
      "loadBalanceCompression" : "DO_NOT_COMPRESS",
      "loadBalanceStrategy" : "DO_NOT_LOAD_BALANCE",
      "name" : "",
      "prioritizers" : [ ],
      "selectedRelationships" : [ "failure", "retry" ],
      "source" : {
        "comments" : "",
        "groupId" : "flow-contents-group",
        "id" : "663e7d81-8ec8-3da7-84bd-c949b112cef7",
        "name" : "LogToSyncTracking",
        "type" : "PROCESSOR"
      },
      "zIndex" : 0
    }, {
      "backPressureDataSizeThreshold" : "1 GB",
      "backPressureObjectThreshold" : 10000,
      "bends" : [ ],
      "componentType" : "CONNECTION",
      "destination" : {
        "groupId" : "flow-contents-group",
        "id" : "31612479-f8a9-3976-a7c9-80c634c046ff",
        "name" : "db-upload-error-out",
        "type" : "OUTPUT_PORT"
      },
      "flowFileExpiration" : "0 sec",
      "groupIdentifier" : "flow-contents-group",
      "identifier" : "646b870d-4421-3799-a130-f38c9ab72202",
      "labelIndex" : 1,
      "loadBalanceCompression" : "DO_NOT_COMPRESS",
      "loadBalanceStrategy" : "DO_NOT_LOAD_BALANCE",
      "name" : "",
      "prioritizers" : [ ],
      "selectedRelationships" : [ "failure" ],
      "source" : {
        "comments" : "",
        "groupId" : "flow-contents-group",
        "id" : "d2d8e805-5521-3cd4-bcdf-100677b6ef6f",
        "name" : "SplitIntoUploadBatches",
        "type" : "PROCESSOR"
      },
      "zIndex" : 0
    }, {
      "backPressureDataSizeThreshold" : "1 GB",
      "backPressureObjectThreshold" : 10000,
      "bends" : [ ],
      "componentType" : "CONNECTION",
      "destination" : {
        "groupId" : "flow-contents-group",
        "id" : "31612479-f8a9-3976-a7c9-80c634c046ff",
        "name" : "db-upload-error-out",
        "type" : "OUTPUT_PORT"
      },
      "flowFileExpiration" : "0 sec",
      "groupIdentifier" : "flow-contents-group",
      "identifier" : "687b9dc1-c1c7-314c-bad9-4ad3ee9475fb",
      "labelIndex" : 1,
      "loadBalanceCompression" : "DO_NOT_COMPRESS",
      "loadBalanceStrategy" : "DO_NOT_LOAD_BALANCE",
      "name" : "",
      "prioritizers" : [ ],
      "selectedRelationships" : [ "unmatched" ],
      "source" : {
        "comments" : "",
        "groupId" : "flow-contents-group",
        "id" : "b4a37b6c-94b8-3b12-880b-b7ad6c999e5c",
        "name" : "RouteByUploadType",
        "type" : "PROCESSOR"
      },
      "zIndex" : 0
    }, {
      "backPressureDataSizeThreshold" : "1 GB",
      "backPressureObjectThreshold" : 10000,
      "bends" : [ ],
      "componentType" : "CONNECTION",
      "destination" : {
        "comments" : "",
        "groupId" : "flow-contents-group",
        "id" : "cece8839-87f4-3fd3-a650-1a05558d21d0",
        "name" : "PathForProduct",
        "type" : "PROCESSOR"
      },
      "flowFileExpiration" : "0 sec",
      "groupIdentifier" : "flow-contents-group",
      "identifier" : "6f1eee9e-ea33-3504-b0e3-883e35b5a3f6",
      "labelIndex" : 1,
      "loadBalanceCompression" : "DO_NOT_COMPRESS",
      "loadBalanceStrategy" : "DO_NOT_LOAD_BALANCE",
      "name" : "",
      "prioritizers" : [ ],
      "selectedRelationships" : [ "route-product" ],
      "source" : {
        "comments" : "",
        "groupId" : "flow-contents-group",
        "id" : "b4a37b6c-94b8-3b12-880b-b7ad6c999e5c",
        "name" : "RouteByUploadType",
        "type" : "PROCESSOR"
      },
      "zIndex" : 0
    }, {
      "backPressureDataSizeThreshold" : "1 GB",
      "backPressureObjectThreshold" : 10000,
      "bends" : [ ],
      "componentType" : "CONNECTION",
      "destination" : {
        "comments" : "",
        "groupId" : "flow-contents-group",
        "id" : "b4a37b6c-94b8-3b12-880b-b7ad6c999e5c",
        "name" : "RouteByUploadType",
        "type" : "PROCESSOR"
      },
      "flowFileExpiration" : "0 sec",
      "groupIdentifier" : "flow-contents-group",
      "identifier" : "762246bf-2813-3bbe-928a-71168ab90ac6",
      "labelIndex" : 1,
      "loadBalanceCompression" : "DO_NOT_COMPRESS",
      "loadBalanceStrategy" : "DO_NOT_LOAD_BALANCE",
      "name" : "",
      "prioritizers" : [ ],
      "selectedRelationships" : [ "splits" ],
      "source" : {
        "comments" : "",
        "groupId" : "flow-contents-group",
        "id" : "d2d8e805-5521-3cd4-bcdf-100677b6ef6f",
        "name" : "SplitIntoUploadBatches",
        "type" : "PROCESSOR"
      },
      "zIndex" : 0
    }, {
      "backPressureDataSizeThreshold" : "1 GB",
      "backPressureObjectThreshold" : 10000,
      "bends" : [ ],
      "componentType" : "CONNECTION",
      "destination" : {
        "comments" : "",
        "groupId" : "flow-contents-group",
        "id" : "11c59787-b8ee-3c3e-92c2-948057eddcd4",
        "name" : "PathForSalesReturn",
        "type" : "PROCESSOR"
      },
      "flowFileExpiration" : "0 sec",
      "groupIdentifier" : "flow-contents-group",
      "identifier" : "85c829df-48cf-3f19-9b0e-f031de3ec9b9",
      "labelIndex" : 1,
      "loadBalanceCompression" : "DO_NOT_COMPRESS",
      "loadBalanceStrategy" : "DO_NOT_LOAD_BALANCE",
      "name" : "",
      "prioritizers" : [ ],
      "selectedRelationships" : [ "route-sales-return" ],
      "source" : {
        "comments" : "",
        "groupId" : "flow-contents-group",
        "id" : "b4a37b6c-94b8-3b12-880b-b7ad6c999e5c",
        "name" : "RouteByUploadType",
        "type" : "PROCESSOR"
      },
      "zIndex" : 0
    }, {
      "backPressureDataSizeThreshold" : "1 GB",
      "backPressureObjectThreshold" : 10000,
      "bends" : [ ],
      "componentType" : "CONNECTION",
      "destination" : {
        "comments" : "",
        "groupId" : "flow-contents-group",
        "id" : "f20cd14c-f020-3783-b947-38ea397c6db8",
        "name" : "PathForSales",
        "type" : "PROCESSOR"
      },
      "flowFileExpiration" : "0 sec",
      "groupIdentifier" : "flow-contents-group",
      "identifier" : "a4f8e115-0f43-3daa-8502-56ce745b6bda",
      "labelIndex" : 1,
      "loadBalanceCompression" : "DO_NOT_COMPRESS",
      "loadBalanceStrategy" : "DO_NOT_LOAD_BALANCE",
      "name" : "",
      "prioritizers" : [ ],
      "selectedRelationships" : [ "route-sales" ],
      "source" : {
        "comments" : "",
        "groupId" : "flow-contents-group",
        "id" : "b4a37b6c-94b8-3b12-880b-b7ad6c999e5c",
        "name" : "RouteByUploadType",
        "type" : "PROCESSOR"
      },
      "zIndex" : 0
    }, {
      "backPressureDataSizeThreshold" : "1 GB",
      "backPressureObjectThreshold" : 10000,
      "bends" : [ ],
      "componentType" : "CONNECTION",
      "destination" : {
        "groupId" : "flow-contents-group",
        "id" : "62027a43-81ab-395c-8b8f-9c8387888bf7",
        "name" : "upload-success-out",
        "type" : "OUTPUT_PORT"
      },
      "flowFileExpiration" : "0 sec",
      "groupIdentifier" : "flow-contents-group",
      "identifier" : "d4d4a1c8-da8b-3e23-92d2-2926b8ef8e18",
      "labelIndex" : 1,
      "loadBalanceCompression" : "DO_NOT_COMPRESS",
      "loadBalanceStrategy" : "DO_NOT_LOAD_BALANCE",
      "name" : "",
      "prioritizers" : [ ],
      "selectedRelationships" : [ "success" ],
      "source" : {
        "comments" : "",
        "groupId" : "flow-contents-group",
        "id" : "663e7d81-8ec8-3da7-84bd-c949b112cef7",
        "name" : "LogToSyncTracking",
        "type" : "PROCESSOR"
      },
      "zIndex" : 0
    }, {
      "backPressureDataSizeThreshold" : "1 GB",
      "backPressureObjectThreshold" : 10000,
      "bends" : [ ],
      "componentType" : "CONNECTION",
      "destination" : {
        "comments" : "",
        "groupId" : "flow-contents-group",
        "id" : "36d95e6e-9bc1-340f-9309-3ac5ce73e17b",
        "name" : "PathForCustomer",
        "type" : "PROCESSOR"
      },
      "flowFileExpiration" : "0 sec",
      "groupIdentifier" : "flow-contents-group",
      "identifier" : "dc3c70a4-5ce5-3bb3-a020-5f81631d75b3",
      "labelIndex" : 1,
      "loadBalanceCompression" : "DO_NOT_COMPRESS",
      "loadBalanceStrategy" : "DO_NOT_LOAD_BALANCE",
      "name" : "",
      "prioritizers" : [ ],
      "selectedRelationships" : [ "route-customer" ],
      "source" : {
        "comments" : "",
        "groupId" : "flow-contents-group",
        "id" : "b4a37b6c-94b8-3b12-880b-b7ad6c999e5c",
        "name" : "RouteByUploadType",
        "type" : "PROCESSOR"
      },
      "zIndex" : 0
    }, {
      "backPressureDataSizeThreshold" : "1 GB",
      "backPressureObjectThreshold" : 10000,
      "bends" : [ ],
      "componentType" : "CONNECTION",
      "destination" : {
        "comments" : "",
        "groupId" : "flow-contents-group",
        "id" : "d2d8e805-5521-3cd4-bcdf-100677b6ef6f",
        "name" : "SplitIntoUploadBatches",
        "type" : "PROCESSOR"
      },
      "flowFileExpiration" : "0 sec",
      "groupIdentifier" : "flow-contents-group",
      "identifier" : "e55a7ca6-3f0e-3872-8ea4-1d36c933725d",
      "labelIndex" : 1,
      "loadBalanceCompression" : "DO_NOT_COMPRESS",
      "loadBalanceStrategy" : "DO_NOT_LOAD_BALANCE",
      "name" : "",
      "prioritizers" : [ ],
      "selectedRelationships" : [ "" ],
      "source" : {
        "groupId" : "flow-contents-group",
        "id" : "2fed12c7-2b9b-3da3-8f28-c0c7742ba70b",
        "name" : "normalized-data-in",
        "type" : "INPUT_PORT"
      },
      "zIndex" : 0
    }, {
      "backPressureDataSizeThreshold" : "1 GB",
      "backPressureObjectThreshold" : 10000,
      "bends" : [ ],
      "componentType" : "CONNECTION",
      "destination" : {
        "comments" : "",
        "groupId" : "flow-contents-group",
        "id" : "f9202b45-38ba-36a5-b538-82d8b66a2d23",
        "name" : "LogUploadResult",
        "type" : "PROCESSOR"
      },
      "flowFileExpiration" : "0 sec",
      "groupIdentifier" : "flow-contents-group",
      "identifier" : "f3f37038-0186-33af-8540-5a959f5185c0",
      "labelIndex" : 1,
      "loadBalanceCompression" : "DO_NOT_COMPRESS",
      "loadBalanceStrategy" : "DO_NOT_LOAD_BALANCE",
      "name" : "",
      "prioritizers" : [ ],
      "selectedRelationships" : [ "Response" ],
      "source" : {
        "comments" : "",
        "groupId" : "flow-contents-group",
        "id" : "36681431-afa3-3fab-9477-d7f2a18272dd",
        "name" : "PostToUploadAPI",
        "type" : "PROCESSOR"
      },
      "zIndex" : 0
    }, {
      "backPressureDataSizeThreshold" : "1 GB",
      "backPressureObjectThreshold" : 10000,
      "bends" : [ ],
      "componentType" : "CONNECTION",
      "destination" : {
        "groupId" : "flow-contents-group",
        "id" : "31612479-f8a9-3976-a7c9-80c634c046ff",
        "name" : "db-upload-error-out",
        "type" : "OUTPUT_PORT"
      },
      "flowFileExpiration" : "0 sec",
      "groupIdentifier" : "flow-contents-group",
      "identifier" : "f5edf051-a53d-34c8-a67a-8a5bd7f812e1",
      "labelIndex" : 1,
      "loadBalanceCompression" : "DO_NOT_COMPRESS",
      "loadBalanceStrategy" : "DO_NOT_LOAD_BALANCE",
      "name" : "",
      "prioritizers" : [ ],
      "selectedRelationships" : [ "Failure", "No Retry", "Retry" ],
      "source" : {
        "comments" : "",
        "groupId" : "flow-contents-group",
        "id" : "36681431-afa3-3fab-9477-d7f2a18272dd",
        "name" : "PostToUploadAPI",
        "type" : "PROCESSOR"
      },
      "zIndex" : 0
    } ],
    "controllerServices" : [ {
      "bulletinLevel" : "WARN",
      "bundle" : {
        "artifact" : "nifi-record-serialization-services-nar",
        "group" : "org.apache.nifi",
        "version" : "2.10.0"
      },
      "comments" : "",
      "componentType" : "CONTROLLER_SERVICE",
      "controllerServiceApis" : [ {
        "bundle" : {
          "artifact" : "nifi-standard-services-api-nar",
          "group" : "org.apache.nifi",
          "version" : "2.10.0"
        },
        "type" : "org.apache.nifi.serialization.RecordReaderFactory"
      } ],
      "groupIdentifier" : "flow-contents-group",
      "identifier" : "46d4987d-9dc9-3a15-9ec3-efb0a8313207",
      "name" : "CSVReader-UploadSplit",
      "properties" : {
        "Schema Text" : "${avro.schema}",
        "CSV Format" : "custom",
        "Quote Character" : "\"",
        "Value Separator" : ",",
        "Treat First Line as Header" : "true",
        "Schema Access Strategy" : "csv-header-derived",
        "Ignore CSV Header Column Names" : "false",
        "Schema Name" : "${schema.name}",
        "Record Separator" : "\\n",
        "Escape Character" : "\\",
        "Trim Double Quote" : "true",
        "Trim Fields" : "true",
        "Allow Duplicate Header Names" : "true",
        "CSV Parser" : "commons-csv",
        "Character Set" : "UTF-8"
      },
      "propertyDescriptors" : {
        "Schema Branch" : {
          "displayName" : "Schema Branch",
          "dynamic" : false,
          "identifiesControllerService" : false,
          "name" : "Schema Branch",
          "sensitive" : false
        },
        "Schema Reference Reader" : {
          "displayName" : "Schema Reference Reader",
          "dynamic" : false,
          "identifiesControllerService" : true,
          "name" : "Schema Reference Reader",
          "sensitive" : false
        },
        "Schema Text" : {
          "displayName" : "Schema Text",
          "dynamic" : false,
          "identifiesControllerService" : false,
          "name" : "Schema Text",
          "sensitive" : false
        },
        "CSV Format" : {
          "displayName" : "CSV Format",
          "dynamic" : false,
          "identifiesControllerService" : false,
          "name" : "CSV Format",
          "sensitive" : false
        },
        "Quote Character" : {
          "displayName" : "Quote Character",
          "dynamic" : false,
          "identifiesControllerService" : false,
          "name" : "Quote Character",
          "sensitive" : false
        },
        "Value Separator" : {
          "displayName" : "Value Separator",
          "dynamic" : false,
          "identifiesControllerService" : false,
          "name" : "Value Separator",
          "sensitive" : false
        },
        "Schema Registry" : {
          "displayName" : "Schema Registry",
          "dynamic" : false,
          "identifiesControllerService" : true,
          "name" : "Schema Registry",
          "sensitive" : false
        },
        "Treat First Line as Header" : {
          "displayName" : "Treat First Line as Header",
          "dynamic" : false,
          "identifiesControllerService" : false,
          "name" : "Treat First Line as Header",
          "sensitive" : false
        },
        "Schema Access Strategy" : {
          "displayName" : "Schema Access Strategy",
          "dynamic" : false,
          "identifiesControllerService" : false,
          "name" : "Schema Access Strategy",
          "sensitive" : false
        },
        "Ignore CSV Header Column Names" : {
          "displayName" : "Ignore CSV Header Column Names",
          "dynamic" : false,
          "identifiesControllerService" : false,
          "name" : "Ignore CSV Header Column Names",
          "sensitive" : false
        },
        "Schema Name" : {
          "displayName" : "Schema Name",
          "dynamic" : false,
          "identifiesControllerService" : false,
          "name" : "Schema Name",
          "sensitive" : false
        },
        "Record Separator" : {
          "displayName" : "Record Separator",
          "dynamic" : false,
          "identifiesControllerService" : false,
          "name" : "Record Separator",
          "sensitive" : false
        },
        "Timestamp Format" : {
          "displayName" : "Timestamp Format",
          "dynamic" : false,
          "identifiesControllerService" : false,
          "name" : "Timestamp Format",
          "sensitive" : false
        },
        "Escape Character" : {
          "displayName" : "Escape Character",
          "dynamic" : false,
          "identifiesControllerService" : false,
          "name" : "Escape Character",
          "sensitive" : false
        },
        "Date Format" : {
          "displayName" : "Date Format",
          "dynamic" : false,
          "identifiesControllerService" : false,
          "name" : "Date Format",
          "sensitive" : false
        },
        "Trim Double Quote" : {
          "displayName" : "Trim Double Quote",
          "dynamic" : false,
          "identifiesControllerService" : false,
          "name" : "Trim Double Quote",
          "sensitive" : false
        },
        "Null String" : {
          "displayName" : "Null String",
          "dynamic" : false,
          "identifiesControllerService" : false,
          "name" : "Null String",
          "sensitive" : false
        },
        "Trim Fields" : {
          "displayName" : "Trim Fields",
          "dynamic" : false,
          "identifiesControllerService" : false,
          "name" : "Trim Fields",
          "sensitive" : false
        },
        "Schema Version" : {
          "displayName" : "Schema Version",
          "dynamic" : false,
          "identifiesControllerService" : false,
          "name" : "Schema Version",
          "sensitive" : false
        },
        "Time Format" : {
          "displayName" : "Time Format",
          "dynamic" : false,
          "identifiesControllerService" : false,
          "name" : "Time Format",
          "sensitive" : false
        },
        "Comment Marker" : {
          "displayName" : "Comment Marker",
          "dynamic" : false,
          "identifiesControllerService" : false,
          "name" : "Comment Marker",
          "sensitive" : false
        },
        "Allow Duplicate Header Names" : {
          "displayName" : "Allow Duplicate Header Names",
          "dynamic" : false,
          "identifiesControllerService" : false,
          "name" : "Allow Duplicate Header Names",
          "sensitive" : false
        },
        "CSV Parser" : {
          "displayName" : "CSV Parser",
          "dynamic" : false,
          "identifiesControllerService" : false,
          "name" : "CSV Parser",
          "sensitive" : false
        },
        "Character Set" : {
          "displayName" : "Character Set",
          "dynamic" : false,
          "identifiesControllerService" : false,
          "name" : "Character Set",
          "sensitive" : false
        }
      },
      "scheduledState" : "DISABLED",
      "type" : "org.apache.nifi.csv.CSVReader"
    }, {
      "bulletinLevel" : "WARN",
      "bundle" : {
        "artifact" : "nifi-oauth2-provider-nar",
        "group" : "org.apache.nifi",
        "version" : "2.10.0"
      },
      "comments" : "",
      "componentType" : "CONTROLLER_SERVICE",
      "controllerServiceApis" : [ {
        "bundle" : {
          "artifact" : "nifi-standard-services-api-nar",
          "group" : "org.apache.nifi",
          "version" : "2.10.0"
        },
        "type" : "org.apache.nifi.oauth2.OAuth2AccessTokenProvider"
      } ],
      "groupIdentifier" : "flow-contents-group",
      "identifier" : "b00b863f-45cb-335d-bb28-86616025dac3",
      "name" : "CasaKeycloakTokenProvider",
      "properties" : {
        "Client ID" : "casa_dashboard",
        "Default Expiration Time" : "1 hour",
        "Grant Type" : "password",
        "HTTP Protocols" : "H2_HTTP_1_1",
        "Refresh Window" : "0 s",
        "Authorization Server URL" : "https://auth.qa.casaretail.ai/realms/casa/protocol/openid-connect/token",
        "Username" : "fashionfolks@gmail.com",
        "Client Authentication Strategy" : "REQUEST_BODY"
      },
      "propertyDescriptors" : {
        "Client ID" : {
          "displayName" : "Client ID",
          "dynamic" : false,
          "identifiesControllerService" : false,
          "name" : "Client ID",
          "sensitive" : false
        },
        "Audience" : {
          "displayName" : "Audience",
          "dynamic" : false,
          "identifiesControllerService" : false,
          "name" : "Audience",
          "sensitive" : false
        },
        "Default Expiration Time" : {
          "displayName" : "Default Expiration Time",
          "dynamic" : false,
          "identifiesControllerService" : false,
          "name" : "Default Expiration Time",
          "sensitive" : false
        },
        "Resource" : {
          "displayName" : "Resource",
          "dynamic" : false,
          "identifiesControllerService" : false,
          "name" : "Resource",
          "sensitive" : false
        },
        "Grant Type" : {
          "displayName" : "Grant Type",
          "dynamic" : false,
          "identifiesControllerService" : false,
          "name" : "Grant Type",
          "sensitive" : false
        },
        "Refresh Token" : {
          "displayName" : "Refresh Token",
          "dynamic" : false,
          "identifiesControllerService" : false,
          "name" : "Refresh Token",
          "sensitive" : true
        },
        "HTTP Protocols" : {
          "displayName" : "HTTP Protocols",
          "dynamic" : false,
          "identifiesControllerService" : false,
          "name" : "HTTP Protocols",
          "sensitive" : false
        },
        "Proxy Configuration Service" : {
          "displayName" : "Proxy Configuration Service",
          "dynamic" : false,
          "identifiesControllerService" : true,
          "name" : "Proxy Configuration Service",
          "sensitive" : false
        },
        "Refresh Window" : {
          "displayName" : "Refresh Window",
          "dynamic" : false,
          "identifiesControllerService" : false,
          "name" : "Refresh Window",
          "sensitive" : false
        },
        "SSL Context Service" : {
          "displayName" : "SSL Context Service",
          "dynamic" : false,
          "identifiesControllerService" : true,
          "name" : "SSL Context Service",
          "sensitive" : false
        },
        "Authorization Server URL" : {
          "displayName" : "Authorization Server URL",
          "dynamic" : false,
          "identifiesControllerService" : false,
          "name" : "Authorization Server URL",
          "sensitive" : false
        },
        "Scope" : {
          "displayName" : "Scope",
          "dynamic" : false,
          "identifiesControllerService" : false,
          "name" : "Scope",
          "sensitive" : false
        },
        "Username" : {
          "displayName" : "Username",
          "dynamic" : false,
          "identifiesControllerService" : false,
          "name" : "Username",
          "sensitive" : false
        },
        "Client Authentication Strategy" : {
          "displayName" : "Client Authentication Strategy",
          "dynamic" : false,
          "identifiesControllerService" : false,
          "name" : "Client Authentication Strategy",
          "sensitive" : false
        },
        "Client Secret" : {
          "displayName" : "Client Secret",
          "dynamic" : false,
          "identifiesControllerService" : false,
          "name" : "Client Secret",
          "sensitive" : true
        },
        "Password" : {
          "displayName" : "Password",
          "dynamic" : false,
          "identifiesControllerService" : false,
          "name" : "Password",
          "sensitive" : true
        }
      },
      "scheduledState" : "DISABLED",
      "type" : "org.apache.nifi.oauth2.StandardOauth2AccessTokenProvider"
    } ],
    "defaultBackPressureDataSizeThreshold" : "1 GB",
    "defaultBackPressureObjectThreshold" : 10000,
    "defaultFlowFileExpiration" : "0 sec",
    "executionEngine" : "INHERITED",
    "externalControllerServiceReferences" : {
      "78e6b768-aeb8-3b84-8046-96f83cf31033" : {
        "identifier" : "78e6b768-aeb8-3b84-8046-96f83cf31033",
        "name" : "CSVRecordSetWriter"
      },
      "f8fe6515-589a-36d7-9cdd-2c3cd1bb0209" : {
        "identifier" : "f8fe6515-589a-36d7-9cdd-2c3cd1bb0209",
        "name" : "DBCPConnectionPool"
      }
    },
    "flowFileConcurrency" : "UNBOUNDED",
    "flowFileOutboundPolicy" : "STREAM_WHEN_AVAILABLE",
    "funnels" : [ ],
    "identifier" : "flow-contents-group",
    "inputPorts" : [ {
      "allowRemoteAccess" : false,
      "componentType" : "INPUT_PORT",
      "concurrentlySchedulableTaskCount" : 1,
      "groupIdentifier" : "flow-contents-group",
      "identifier" : "2fed12c7-2b9b-3da3-8f28-c0c7742ba70b",
      "name" : "normalized-data-in",
      "portFunction" : "STANDARD",
      "position" : {
        "x" : 0.0,
        "y" : 0.0
      },
      "scheduledState" : "ENABLED",
      "type" : "INPUT_PORT"
    } ],
    "labels" : [ ],
    "maxConcurrentTasks" : 1,
    "name" : "08-Database-Upload",
    "outputPorts" : [ {
      "allowRemoteAccess" : false,
      "componentType" : "OUTPUT_PORT",
      "concurrentlySchedulableTaskCount" : 1,
      "groupIdentifier" : "flow-contents-group",
      "identifier" : "31612479-f8a9-3976-a7c9-80c634c046ff",
      "name" : "db-upload-error-out",
      "portFunction" : "STANDARD",
      "position" : {
        "x" : 2112.0,
        "y" : 528.0
      },
      "scheduledState" : "ENABLED",
      "type" : "OUTPUT_PORT"
    }, {
      "allowRemoteAccess" : false,
      "componentType" : "OUTPUT_PORT",
      "concurrentlySchedulableTaskCount" : 1,
      "groupIdentifier" : "flow-contents-group",
      "identifier" : "62027a43-81ab-395c-8b8f-9c8387888bf7",
      "name" : "upload-success-out",
      "portFunction" : "STANDARD",
      "position" : {
        "x" : 6312.0,
        "y" : 248.0
      },
      "scheduledState" : "ENABLED",
      "type" : "OUTPUT_PORT"
    } ],
    "position" : {
      "x" : 0.0,
      "y" : 0.0
    },
    "processGroups" : [ ],
    "processors" : [ {
      "autoTerminatedRelationships" : [ ],
      "backoffMechanism" : "PENALIZE_FLOWFILE",
      "bulletinLevel" : "WARN",
      "bundle" : {
        "artifact" : "nifi-update-attribute-nar",
        "group" : "org.apache.nifi",
        "version" : "2.10.0"
      },
      "comments" : "",
      "componentType" : "PROCESSOR",
      "concurrentlySchedulableTaskCount" : 1,
      "executionNode" : "ALL",
      "groupIdentifier" : "flow-contents-group",
      "identifier" : "11c59787-b8ee-3c3e-92c2-948057eddcd4",
      "maxBackoffPeriod" : "10 mins",
      "name" : "PathForSalesReturn",
      "penaltyDuration" : "30 sec",
      "position" : {
        "x" : 3500.0,
        "y" : 200.0
      },
      "properties" : {
        "filename" : "sales_return.csv",
        "Store State" : "Do not store state",
        "upload_api_url" : "https://api.casaqa.ajira.tech/system-upload/bill-upload/${bu_id}?tenantId=${tenant_id}&email=systemadmin@casaretail.ai",
        "Cache Value Lookup Cache Size" : "100",
        "multipart_field_name" : "bill"
      },
      "propertyDescriptors" : {
        "Delete Attributes Expression" : {
          "displayName" : "Delete Attributes Expression",
          "dynamic" : false,
          "identifiesControllerService" : false,
          "name" : "Delete Attributes Expression",
          "sensitive" : false
        },
        "filename" : {
          "displayName" : "filename",
          "dynamic" : true,
          "identifiesControllerService" : false,
          "name" : "filename",
          "sensitive" : false
        },
        "Store State" : {
          "displayName" : "Store State",
          "dynamic" : false,
          "identifiesControllerService" : false,
          "name" : "Store State",
          "sensitive" : false
        },
        "upload_api_url" : {
          "displayName" : "upload_api_url",
          "dynamic" : true,
          "identifiesControllerService" : false,
          "name" : "upload_api_url",
          "sensitive" : false
        },
        "Cache Value Lookup Cache Size" : {
          "displayName" : "Cache Value Lookup Cache Size",
          "dynamic" : false,
          "identifiesControllerService" : false,
          "name" : "Cache Value Lookup Cache Size",
          "sensitive" : false
        },
        "Stateful Variables Initial Value" : {
          "displayName" : "Stateful Variables Initial Value",
          "dynamic" : false,
          "identifiesControllerService" : false,
          "name" : "Stateful Variables Initial Value",
          "sensitive" : false
        },
        "multipart_field_name" : {
          "displayName" : "multipart_field_name",
          "dynamic" : true,
          "identifiesControllerService" : false,
          "name" : "multipart_field_name",
          "sensitive" : false
        }
      },
      "retriedRelationships" : [ ],
      "retryCount" : 10,
      "runDurationMillis" : 25,
      "scheduledState" : "ENABLED",
      "schedulingPeriod" : "0 sec",
      "schedulingStrategy" : "TIMER_DRIVEN",
      "style" : { },
      "type" : "org.apache.nifi.processors.attributes.UpdateAttribute",
      "yieldDuration" : "1 sec"
    }, {
      "autoTerminatedRelationships" : [ "Original" ],
      "backoffMechanism" : "PENALIZE_FLOWFILE",
      "bulletinLevel" : "WARN",
      "bundle" : {
        "artifact" : "nifi-standard-nar",
        "group" : "org.apache.nifi",
        "version" : "2.10.0"
      },
      "comments" : "",
      "componentType" : "PROCESSOR",
      "concurrentlySchedulableTaskCount" : 1,
      "executionNode" : "ALL",
      "groupIdentifier" : "flow-contents-group",
      "identifier" : "36681431-afa3-3fab-9477-d7f2a18272dd",
      "maxBackoffPeriod" : "10 mins",
      "name" : "PostToUploadAPI",
      "penaltyDuration" : "30 sec",
      "position" : {
        "x" : 4232.0,
        "y" : 1144.0
      },
      "properties" : {
        "Request Content-Encoding" : "DISABLED",
        "Request Multipart Form-Data Filename Enabled" : "true",
        "Request Chunked Transfer-Encoding Enabled" : "false",
        "HTTP/2 Disabled" : "False",
        "Connection Timeout" : "30 secs",
        "Response Cookie Strategy" : "DISABLED",
        "Socket Read Timeout" : "120 secs",
        "Socket Idle Connections" : "5",
        "Request Body Enabled" : "true",
        "OAuth2 Access Token Refresh Strategy" : "ON_TOKEN_EXPIRATION",
        "HTTP URL" : "${upload_api_url}",
        "Socket Idle Timeout" : "5 mins",
        "Response Redirects Enabled" : "True",
        "Socket Write Timeout" : "15 secs",
        "Response FlowFile Naming Strategy" : "RANDOM",
        "Response Cache Enabled" : "false",
        "Request Date Header Enabled" : "True",
        "Request Failure Penalization Enabled" : "false",
        "Response Body Attribute Size" : "2048",
        "Response Generation Required" : "true",
        "Response Header Request Attributes Enabled" : "false",
        "HTTP Method" : "POST",
        "Request Content-Type" : "text/csv",
        "Response Body Attribute Name" : "api_response_body",
        "Request Digest Authentication Enabled" : "false",
        "Request Multipart Form-Data Name" : "${multipart_field_name}",
        "Response Cache Size" : "10MB",
        "Response Body Ignored" : "false"
      },
      "propertyDescriptors" : {
        "Request Content-Encoding" : {
          "displayName" : "Request Content-Encoding",
          "dynamic" : false,
          "identifiesControllerService" : false,
          "name" : "Request Content-Encoding",
          "sensitive" : false
        },
        "Request Multipart Form-Data Filename Enabled" : {
          "displayName" : "Request Multipart Form-Data Filename Enabled",
          "dynamic" : false,
          "identifiesControllerService" : false,
          "name" : "Request Multipart Form-Data Filename Enabled",
          "sensitive" : false
        },
        "Request Chunked Transfer-Encoding Enabled" : {
          "displayName" : "Request Chunked Transfer-Encoding Enabled",
          "dynamic" : false,
          "identifiesControllerService" : false,
          "name" : "Request Chunked Transfer-Encoding Enabled",
          "sensitive" : false
        },
        "Response Header Request Attributes Prefix" : {
          "displayName" : "Response Header Request Attributes Prefix",
          "dynamic" : false,
          "identifiesControllerService" : false,
          "name" : "Response Header Request Attributes Prefix",
          "sensitive" : false
        },
        "Proxy Configuration Service" : {
          "displayName" : "Proxy Configuration Service",
          "dynamic" : false,
          "identifiesControllerService" : true,
          "name" : "Proxy Configuration Service",
          "sensitive" : false
        },
        "HTTP/2 Disabled" : {
          "displayName" : "HTTP/2 Disabled",
          "dynamic" : false,
          "identifiesControllerService" : false,
          "name" : "HTTP/2 Disabled",
          "sensitive" : false
        },
        "Connection Timeout" : {
          "displayName" : "Connection Timeout",
          "dynamic" : false,
          "identifiesControllerService" : false,
          "name" : "Connection Timeout",
          "sensitive" : false
        },
        "Response Cookie Strategy" : {
          "displayName" : "Response Cookie Strategy",
          "dynamic" : false,
          "identifiesControllerService" : false,
          "name" : "Response Cookie Strategy",
          "sensitive" : false
        },
        "Request Password" : {
          "displayName" : "Request Password",
          "dynamic" : false,
          "identifiesControllerService" : false,
          "name" : "Request Password",
          "sensitive" : true
        },
        "Socket Read Timeout" : {
          "displayName" : "Socket Read Timeout",
          "dynamic" : false,
          "identifiesControllerService" : false,
          "name" : "Socket Read Timeout",
          "sensitive" : false
        },
        "Socket Idle Connections" : {
          "displayName" : "Socket Idle Connections",
          "dynamic" : false,
          "identifiesControllerService" : false,
          "name" : "Socket Idle Connections",
          "sensitive" : false
        },
        "Request Body Enabled" : {
          "displayName" : "Request Body Enabled",
          "dynamic" : false,
          "identifiesControllerService" : false,
          "name" : "Request Body Enabled",
          "sensitive" : false
        },
        "OAuth2 Access Token Refresh Strategy" : {
          "displayName" : "OAuth2 Access Token Refresh Strategy",
          "dynamic" : false,
          "identifiesControllerService" : false,
          "name" : "OAuth2 Access Token Refresh Strategy",
          "sensitive" : false
        },
        "HTTP URL" : {
          "displayName" : "HTTP URL",
          "dynamic" : false,
          "identifiesControllerService" : false,
          "name" : "HTTP URL",
          "sensitive" : false
        },
        "Request OAuth2 Access Token Provider" : {
          "displayName" : "Request OAuth2 Access Token Provider",
          "dynamic" : false,
          "identifiesControllerService" : true,
          "name" : "Request OAuth2 Access Token Provider",
          "sensitive" : false
        },
        "Socket Idle Timeout" : {
          "displayName" : "Socket Idle Timeout",
          "dynamic" : false,
          "identifiesControllerService" : false,
          "name" : "Socket Idle Timeout",
          "sensitive" : false
        },
        "Response Redirects Enabled" : {
          "displayName" : "Response Redirects Enabled",
          "dynamic" : false,
          "identifiesControllerService" : false,
          "name" : "Response Redirects Enabled",
          "sensitive" : false
        },
        "rule-service-token" : {
          "displayName" : "rule-service-token",
          "dynamic" : true,
          "identifiesControllerService" : false,
          "name" : "rule-service-token",
          "sensitive" : true
        },
        "Socket Write Timeout" : {
          "displayName" : "Socket Write Timeout",
          "dynamic" : false,
          "identifiesControllerService" : false,
          "name" : "Socket Write Timeout",
          "sensitive" : false
        },
        "Request Header Attributes Pattern" : {
          "displayName" : "Request Header Attributes Pattern",
          "dynamic" : false,
          "identifiesControllerService" : false,
          "name" : "Request Header Attributes Pattern",
          "sensitive" : false
        },
        "Response FlowFile Naming Strategy" : {
          "displayName" : "Response FlowFile Naming Strategy",
          "dynamic" : false,
          "identifiesControllerService" : false,
          "name" : "Response FlowFile Naming Strategy",
          "sensitive" : false
        },
        "Response Cache Enabled" : {
          "displayName" : "Response Cache Enabled",
          "dynamic" : false,
          "identifiesControllerService" : false,
          "name" : "Response Cache Enabled",
          "sensitive" : false
        },
        "Request Date Header Enabled" : {
          "displayName" : "Request Date Header Enabled",
          "dynamic" : false,
          "identifiesControllerService" : false,
          "name" : "Request Date Header Enabled",
          "sensitive" : false
        },
        "Request Failure Penalization Enabled" : {
          "displayName" : "Request Failure Penalization Enabled",
          "dynamic" : false,
          "identifiesControllerService" : false,
          "name" : "Request Failure Penalization Enabled",
          "sensitive" : false
        },
        "Response Body Attribute Size" : {
          "displayName" : "Response Body Attribute Size",
          "dynamic" : false,
          "identifiesControllerService" : false,
          "name" : "Response Body Attribute Size",
          "sensitive" : false
        },
        "SSL Context Service" : {
          "displayName" : "SSL Context Service",
          "dynamic" : false,
          "identifiesControllerService" : true,
          "name" : "SSL Context Service",
          "sensitive" : false
        },
        "Response Generation Required" : {
          "displayName" : "Response Generation Required",
          "dynamic" : false,
          "identifiesControllerService" : false,
          "name" : "Response Generation Required",
          "sensitive" : false
        },
        "Request User-Agent" : {
          "displayName" : "Request User-Agent",
          "dynamic" : false,
          "identifiesControllerService" : false,
          "name" : "Request User-Agent",
          "sensitive" : false
        },
        "Response Header Request Attributes Enabled" : {
          "displayName" : "Response Header Request Attributes Enabled",
          "dynamic" : false,
          "identifiesControllerService" : false,
          "name" : "Response Header Request Attributes Enabled",
          "sensitive" : false
        },
        "HTTP Method" : {
          "displayName" : "HTTP Method",
          "dynamic" : false,
          "identifiesControllerService" : false,
          "name" : "HTTP Method",
          "sensitive" : false
        },
        "Request Username" : {
          "displayName" : "Request Username",
          "dynamic" : false,
          "identifiesControllerService" : false,
          "name" : "Request Username",
          "sensitive" : false
        },
        "Request Content-Type" : {
          "displayName" : "Request Content-Type",
          "dynamic" : false,
          "identifiesControllerService" : false,
          "name" : "Request Content-Type",
          "sensitive" : false
        },
        "Response Body Attribute Name" : {
          "displayName" : "Response Body Attribute Name",
          "dynamic" : false,
          "identifiesControllerService" : false,
          "name" : "Response Body Attribute Name",
          "sensitive" : false
        },
        "Request Digest Authentication Enabled" : {
          "displayName" : "Request Digest Authentication Enabled",
          "dynamic" : false,
          "identifiesControllerService" : false,
          "name" : "Request Digest Authentication Enabled",
          "sensitive" : false
        },
        "Request Multipart Form-Data Name" : {
          "displayName" : "Request Multipart Form-Data Name",
          "dynamic" : false,
          "identifiesControllerService" : false,
          "name" : "Request Multipart Form-Data Name",
          "sensitive" : false
        },
        "Response Cache Size" : {
          "displayName" : "Response Cache Size",
          "dynamic" : false,
          "identifiesControllerService" : false,
          "name" : "Response Cache Size",
          "sensitive" : false
        },
        "Response Body Ignored" : {
          "displayName" : "Response Body Ignored",
          "dynamic" : false,
          "identifiesControllerService" : false,
          "name" : "Response Body Ignored",
          "sensitive" : false
        }
      },
      "retriedRelationships" : [ ],
      "retryCount" : 10,
      "runDurationMillis" : 0,
      "scheduledState" : "ENABLED",
      "schedulingPeriod" : "0 sec",
      "schedulingStrategy" : "TIMER_DRIVEN",
      "style" : { },
      "type" : "org.apache.nifi.processors.standard.InvokeHTTP",
      "yieldDuration" : "1 sec"
    }, {
      "autoTerminatedRelationships" : [ ],
      "backoffMechanism" : "PENALIZE_FLOWFILE",
      "bulletinLevel" : "WARN",
      "bundle" : {
        "artifact" : "nifi-update-attribute-nar",
        "group" : "org.apache.nifi",
        "version" : "2.10.0"
      },
      "comments" : "",
      "componentType" : "PROCESSOR",
      "concurrentlySchedulableTaskCount" : 1,
      "executionNode" : "ALL",
      "groupIdentifier" : "flow-contents-group",
      "identifier" : "36d95e6e-9bc1-340f-9309-3ac5ce73e17b",
      "maxBackoffPeriod" : "10 mins",
      "name" : "PathForCustomer",
      "penaltyDuration" : "30 sec",
      "position" : {
        "x" : 1752.0,
        "y" : 664.0
      },
      "properties" : {
        "filename" : "customer.csv",
        "Store State" : "Do not store state",
        "upload_api_url" : "https://api.casaqa.ajira.tech/system-upload/billupload/customer_upload/${bu_id}?tenantId=${tenant_id}&email=systemadmin@casaretail.ai",
        "Cache Value Lookup Cache Size" : "100",
        "multipart_field_name" : "uploadFile"
      },
      "propertyDescriptors" : {
        "Delete Attributes Expression" : {
          "displayName" : "Delete Attributes Expression",
          "dynamic" : false,
          "identifiesControllerService" : false,
          "name" : "Delete Attributes Expression",
          "sensitive" : false
        },
        "filename" : {
          "displayName" : "filename",
          "dynamic" : true,
          "identifiesControllerService" : false,
          "name" : "filename",
          "sensitive" : false
        },
        "Store State" : {
          "displayName" : "Store State",
          "dynamic" : false,
          "identifiesControllerService" : false,
          "name" : "Store State",
          "sensitive" : false
        },
        "upload_api_url" : {
          "displayName" : "upload_api_url",
          "dynamic" : true,
          "identifiesControllerService" : false,
          "name" : "upload_api_url",
          "sensitive" : false
        },
        "Cache Value Lookup Cache Size" : {
          "displayName" : "Cache Value Lookup Cache Size",
          "dynamic" : false,
          "identifiesControllerService" : false,
          "name" : "Cache Value Lookup Cache Size",
          "sensitive" : false
        },
        "Stateful Variables Initial Value" : {
          "displayName" : "Stateful Variables Initial Value",
          "dynamic" : false,
          "identifiesControllerService" : false,
          "name" : "Stateful Variables Initial Value",
          "sensitive" : false
        },
        "multipart_field_name" : {
          "displayName" : "multipart_field_name",
          "dynamic" : true,
          "identifiesControllerService" : false,
          "name" : "multipart_field_name",
          "sensitive" : false
        }
      },
      "retriedRelationships" : [ ],
      "retryCount" : 10,
      "runDurationMillis" : 25,
      "scheduledState" : "ENABLED",
      "schedulingPeriod" : "0 sec",
      "schedulingStrategy" : "TIMER_DRIVEN",
      "style" : { },
      "type" : "org.apache.nifi.processors.attributes.UpdateAttribute",
      "yieldDuration" : "1 sec"
    }, {
      "autoTerminatedRelationships" : [ "failure" ],
      "backoffMechanism" : "PENALIZE_FLOWFILE",
      "bulletinLevel" : "WARN",
      "bundle" : {
        "artifact" : "nifi-standard-nar",
        "group" : "org.apache.nifi",
        "version" : "2.10.0"
      },
      "comments" : "",
      "componentType" : "PROCESSOR",
      "concurrentlySchedulableTaskCount" : 1,
      "executionNode" : "ALL",
      "groupIdentifier" : "flow-contents-group",
      "identifier" : "52dd80d1-045a-3bbc-ae35-9275fcbfa4c7",
      "maxBackoffPeriod" : "10 mins",
      "name" : "CreateInsertStatement",
      "penaltyDuration" : "30 sec",
      "position" : {
        "x" : 4560.0,
        "y" : -96.0
      },
      "properties" : {
        "Replacement Value" : "INSERT INTO public.sync_tracking (config_id, tenant_id, bu_id, upload_type, file_name, last_sync_value, records_processed, status, sync_start_time, sync_end_time) VALUES (${job_id}, ${tenant_id}, ${bu_id}, '${upload_type}', '${source_file_name}', '${last_sync_value}', ${record.count}, 'SUCCESS', CURRENT_TIMESTAMP, CURRENT_TIMESTAMP);",
        "Search Value" : "(?s)(^.*$)",
        "Evaluation Mode" : "Line-by-Line",
        "Line-by-Line Evaluation Mode" : "All",
        "Character Set" : "UTF-8",
        "Maximum Buffer Size" : "1 MB",
        "Replacement Strategy" : "Always Replace"
      },
      "propertyDescriptors" : {
        "Replacement Value" : {
          "displayName" : "Replacement Value",
          "dynamic" : false,
          "identifiesControllerService" : false,
          "name" : "Replacement Value",
          "sensitive" : false
        },
        "Search Value" : {
          "displayName" : "Search Value",
          "dynamic" : false,
          "identifiesControllerService" : false,
          "name" : "Search Value",
          "sensitive" : false
        },
        "Evaluation Mode" : {
          "displayName" : "Evaluation Mode",
          "dynamic" : false,
          "identifiesControllerService" : false,
          "name" : "Evaluation Mode",
          "sensitive" : false
        },
        "Text to Prepend" : {
          "displayName" : "Text to Prepend",
          "dynamic" : false,
          "identifiesControllerService" : false,
          "name" : "Text to Prepend",
          "sensitive" : false
        },
        "Line-by-Line Evaluation Mode" : {
          "displayName" : "Line-by-Line Evaluation Mode",
          "dynamic" : false,
          "identifiesControllerService" : false,
          "name" : "Line-by-Line Evaluation Mode",
          "sensitive" : false
        },
        "Character Set" : {
          "displayName" : "Character Set",
          "dynamic" : false,
          "identifiesControllerService" : false,
          "name" : "Character Set",
          "sensitive" : false
        },
        "Maximum Buffer Size" : {
          "displayName" : "Maximum Buffer Size",
          "dynamic" : false,
          "identifiesControllerService" : false,
          "name" : "Maximum Buffer Size",
          "sensitive" : false
        },
        "Replacement Strategy" : {
          "displayName" : "Replacement Strategy",
          "dynamic" : false,
          "identifiesControllerService" : false,
          "name" : "Replacement Strategy",
          "sensitive" : false
        },
        "Text to Append" : {
          "displayName" : "Text to Append",
          "dynamic" : false,
          "identifiesControllerService" : false,
          "name" : "Text to Append",
          "sensitive" : false
        }
      },
      "retriedRelationships" : [ ],
      "retryCount" : 10,
      "runDurationMillis" : 25,
      "scheduledState" : "ENABLED",
      "schedulingPeriod" : "0 sec",
      "schedulingStrategy" : "TIMER_DRIVEN",
      "style" : { },
      "type" : "org.apache.nifi.processors.standard.ReplaceText",
      "yieldDuration" : "1 sec"
    }, {
      "autoTerminatedRelationships" : [ ],
      "backoffMechanism" : "PENALIZE_FLOWFILE",
      "bulletinLevel" : "WARN",
      "bundle" : {
        "artifact" : "nifi-standard-nar",
        "group" : "org.apache.nifi",
        "version" : "2.10.0"
      },
      "comments" : "",
      "componentType" : "PROCESSOR",
      "concurrentlySchedulableTaskCount" : 1,
      "executionNode" : "ALL",
      "groupIdentifier" : "flow-contents-group",
      "identifier" : "663e7d81-8ec8-3da7-84bd-c949b112cef7",
      "maxBackoffPeriod" : "10 mins",
      "name" : "LogToSyncTracking",
      "penaltyDuration" : "30 sec",
      "position" : {
        "x" : 5500.0,
        "y" : 200.0
      },
      "properties" : {
        "Support Fragmented Transactions" : "false",
        "Database Session AutoCommit" : "false",
        "Batch Size" : "100",
        "Obtain Generated Keys" : "false",
        "Rollback On Failure" : "false",
        "JDBC Connection Pool" : "f8fe6515-589a-36d7-9cdd-2c3cd1bb0209"
      },
      "propertyDescriptors" : {
        "SQL Statement" : {
          "displayName" : "SQL Statement",
          "dynamic" : false,
          "identifiesControllerService" : false,
          "name" : "SQL Statement",
          "sensitive" : false
        },
        "Support Fragmented Transactions" : {
          "displayName" : "Support Fragmented Transactions",
          "dynamic" : false,
          "identifiesControllerService" : false,
          "name" : "Support Fragmented Transactions",
          "sensitive" : false
        },
        "Database Session AutoCommit" : {
          "displayName" : "Database Session AutoCommit",
          "dynamic" : false,
          "identifiesControllerService" : false,
          "name" : "Database Session AutoCommit",
          "sensitive" : false
        },
        "Transaction Timeout" : {
          "displayName" : "Transaction Timeout",
          "dynamic" : false,
          "identifiesControllerService" : false,
          "name" : "Transaction Timeout",
          "sensitive" : false
        },
        "Batch Size" : {
          "displayName" : "Batch Size",
          "dynamic" : false,
          "identifiesControllerService" : false,
          "name" : "Batch Size",
          "sensitive" : false
        },
        "Obtain Generated Keys" : {
          "displayName" : "Obtain Generated Keys",
          "dynamic" : false,
          "identifiesControllerService" : false,
          "name" : "Obtain Generated Keys",
          "sensitive" : false
        },
        "Rollback On Failure" : {
          "displayName" : "Rollback On Failure",
          "dynamic" : false,
          "identifiesControllerService" : false,
          "name" : "Rollback On Failure",
          "sensitive" : false
        },
        "JDBC Connection Pool" : {
          "displayName" : "JDBC Connection Pool",
          "dynamic" : false,
          "identifiesControllerService" : true,
          "name" : "JDBC Connection Pool",
          "sensitive" : false
        }
      },
      "retriedRelationships" : [ ],
      "retryCount" : 10,
      "runDurationMillis" : 0,
      "scheduledState" : "ENABLED",
      "schedulingPeriod" : "0 sec",
      "schedulingStrategy" : "TIMER_DRIVEN",
      "style" : { },
      "type" : "org.apache.nifi.processors.standard.PutSQL",
      "yieldDuration" : "1 sec"
    }, {
      "autoTerminatedRelationships" : [ ],
      "backoffMechanism" : "PENALIZE_FLOWFILE",
      "bulletinLevel" : "WARN",
      "bundle" : {
        "artifact" : "nifi-standard-nar",
        "group" : "org.apache.nifi",
        "version" : "2.10.0"
      },
      "comments" : "",
      "componentType" : "PROCESSOR",
      "concurrentlySchedulableTaskCount" : 1,
      "executionNode" : "ALL",
      "groupIdentifier" : "flow-contents-group",
      "identifier" : "b4a37b6c-94b8-3b12-880b-b7ad6c999e5c",
      "maxBackoffPeriod" : "10 mins",
      "name" : "RouteByUploadType",
      "penaltyDuration" : "30 sec",
      "position" : {
        "x" : 816.0,
        "y" : 216.0
      },
      "properties" : {
        "Routing Strategy" : "Route to Property name",
        "route-product" : "${upload_type:equals('PRODUCT')}",
        "route-customer" : "${upload_type:equals('CUSTOMER')}",
        "route-sales" : "${upload_type:equals('SALES')}",
        "route-sales-return" : "${upload_type:equals('SALES_RETURN')}"
      },
      "propertyDescriptors" : {
        "Routing Strategy" : {
          "displayName" : "Routing Strategy",
          "dynamic" : false,
          "identifiesControllerService" : false,
          "name" : "Routing Strategy",
          "sensitive" : false
        },
        "route-product" : {
          "displayName" : "route-product",
          "dynamic" : true,
          "identifiesControllerService" : false,
          "name" : "route-product",
          "sensitive" : false
        },
        "route-customer" : {
          "displayName" : "route-customer",
          "dynamic" : true,
          "identifiesControllerService" : false,
          "name" : "route-customer",
          "sensitive" : false
        },
        "route-sales" : {
          "displayName" : "route-sales",
          "dynamic" : true,
          "identifiesControllerService" : false,
          "name" : "route-sales",
          "sensitive" : false
        },
        "route-sales-return" : {
          "displayName" : "route-sales-return",
          "dynamic" : true,
          "identifiesControllerService" : false,
          "name" : "route-sales-return",
          "sensitive" : false
        }
      },
      "retriedRelationships" : [ ],
      "retryCount" : 10,
      "runDurationMillis" : 25,
      "scheduledState" : "ENABLED",
      "schedulingPeriod" : "0 sec",
      "schedulingStrategy" : "TIMER_DRIVEN",
      "style" : { },
      "type" : "org.apache.nifi.processors.standard.RouteOnAttribute",
      "yieldDuration" : "1 sec"
    }, {
      "autoTerminatedRelationships" : [ ],
      "backoffMechanism" : "PENALIZE_FLOWFILE",
      "bulletinLevel" : "WARN",
      "bundle" : {
        "artifact" : "nifi-update-attribute-nar",
        "group" : "org.apache.nifi",
        "version" : "2.10.0"
      },
      "comments" : "",
      "componentType" : "PROCESSOR",
      "concurrentlySchedulableTaskCount" : 1,
      "executionNode" : "ALL",
      "groupIdentifier" : "flow-contents-group",
      "identifier" : "cece8839-87f4-3fd3-a650-1a05558d21d0",
      "maxBackoffPeriod" : "10 mins",
      "name" : "PathForProduct",
      "penaltyDuration" : "30 sec",
      "position" : {
        "x" : 1936.0,
        "y" : 1192.0
      },
      "properties" : {
        "filename" : "product.csv",
        "Store State" : "Do not store state",
        "upload_api_url" : "https://api.casaqa.ajira.tech/system-upload/billupload/product_upload/${bu_id}?tenantId=${tenant_id}&email=systemadmin@casaretail.ai",
        "Cache Value Lookup Cache Size" : "100",
        "multipart_field_name" : "uploadFile"
      },
      "propertyDescriptors" : {
        "Delete Attributes Expression" : {
          "displayName" : "Delete Attributes Expression",
          "dynamic" : false,
          "identifiesControllerService" : false,
          "name" : "Delete Attributes Expression",
          "sensitive" : false
        },
        "filename" : {
          "displayName" : "filename",
          "dynamic" : true,
          "identifiesControllerService" : false,
          "name" : "filename",
          "sensitive" : false
        },
        "Store State" : {
          "displayName" : "Store State",
          "dynamic" : false,
          "identifiesControllerService" : false,
          "name" : "Store State",
          "sensitive" : false
        },
        "upload_api_url" : {
          "displayName" : "upload_api_url",
          "dynamic" : true,
          "identifiesControllerService" : false,
          "name" : "upload_api_url",
          "sensitive" : false
        },
        "Cache Value Lookup Cache Size" : {
          "displayName" : "Cache Value Lookup Cache Size",
          "dynamic" : false,
          "identifiesControllerService" : false,
          "name" : "Cache Value Lookup Cache Size",
          "sensitive" : false
        },
        "Stateful Variables Initial Value" : {
          "displayName" : "Stateful Variables Initial Value",
          "dynamic" : false,
          "identifiesControllerService" : false,
          "name" : "Stateful Variables Initial Value",
          "sensitive" : false
        },
        "multipart_field_name" : {
          "displayName" : "multipart_field_name",
          "dynamic" : true,
          "identifiesControllerService" : false,
          "name" : "multipart_field_name",
          "sensitive" : false
        }
      },
      "retriedRelationships" : [ ],
      "retryCount" : 10,
      "runDurationMillis" : 25,
      "scheduledState" : "ENABLED",
      "schedulingPeriod" : "0 sec",
      "schedulingStrategy" : "TIMER_DRIVEN",
      "style" : { },
      "type" : "org.apache.nifi.processors.attributes.UpdateAttribute",
      "yieldDuration" : "1 sec"
    }, {
      "autoTerminatedRelationships" : [ "original" ],
      "backoffMechanism" : "PENALIZE_FLOWFILE",
      "bulletinLevel" : "WARN",
      "bundle" : {
        "artifact" : "nifi-standard-nar",
        "group" : "org.apache.nifi",
        "version" : "2.10.0"
      },
      "comments" : "",
      "componentType" : "PROCESSOR",
      "concurrentlySchedulableTaskCount" : 1,
      "executionNode" : "ALL",
      "groupIdentifier" : "flow-contents-group",
      "identifier" : "d2d8e805-5521-3cd4-bcdf-100677b6ef6f",
      "maxBackoffPeriod" : "10 mins",
      "name" : "SplitIntoUploadBatches",
      "penaltyDuration" : "30 sec",
      "position" : {
        "x" : -232.0,
        "y" : 320.0
      },
      "properties" : {
        "Record Writer" : "78e6b768-aeb8-3b84-8046-96f83cf31033",
        "Record Reader" : "46d4987d-9dc9-3a15-9ec3-efb0a8313207",
        "Records Per Split" : "50000"
      },
      "propertyDescriptors" : {
        "Record Writer" : {
          "displayName" : "Record Writer",
          "dynamic" : false,
          "identifiesControllerService" : true,
          "name" : "Record Writer",
          "sensitive" : false
        },
        "Record Reader" : {
          "displayName" : "Record Reader",
          "dynamic" : false,
          "identifiesControllerService" : true,
          "name" : "Record Reader",
          "sensitive" : false
        },
        "Records Per Split" : {
          "displayName" : "Records Per Split",
          "dynamic" : false,
          "identifiesControllerService" : false,
          "name" : "Records Per Split",
          "sensitive" : false
        }
      },
      "retriedRelationships" : [ ],
      "retryCount" : 10,
      "runDurationMillis" : 0,
      "scheduledState" : "ENABLED",
      "schedulingPeriod" : "0 sec",
      "schedulingStrategy" : "TIMER_DRIVEN",
      "style" : { },
      "type" : "org.apache.nifi.processors.standard.SplitRecord",
      "yieldDuration" : "1 sec"
    }, {
      "autoTerminatedRelationships" : [ ],
      "backoffMechanism" : "PENALIZE_FLOWFILE",
      "bulletinLevel" : "WARN",
      "bundle" : {
        "artifact" : "nifi-update-attribute-nar",
        "group" : "org.apache.nifi",
        "version" : "2.10.0"
      },
      "comments" : "",
      "componentType" : "PROCESSOR",
      "concurrentlySchedulableTaskCount" : 1,
      "executionNode" : "ALL",
      "groupIdentifier" : "flow-contents-group",
      "identifier" : "f20cd14c-f020-3783-b947-38ea397c6db8",
      "maxBackoffPeriod" : "10 mins",
      "name" : "PathForSales",
      "penaltyDuration" : "30 sec",
      "position" : {
        "x" : 1800.0,
        "y" : -72.0
      },
      "properties" : {
        "filename" : "bill.csv",
        "Store State" : "Do not store state",
        "upload_api_url" : "https://api.casaqa.ajira.tech/system-upload/bill-upload/${bu_id}?tenantId=${tenant_id}&email=systemadmin@casaretail.ai",
        "Cache Value Lookup Cache Size" : "100",
        "multipart_field_name" : "bill"
      },
      "propertyDescriptors" : {
        "Delete Attributes Expression" : {
          "displayName" : "Delete Attributes Expression",
          "dynamic" : false,
          "identifiesControllerService" : false,
          "name" : "Delete Attributes Expression",
          "sensitive" : false
        },
        "filename" : {
          "displayName" : "filename",
          "dynamic" : true,
          "identifiesControllerService" : false,
          "name" : "filename",
          "sensitive" : false
        },
        "Store State" : {
          "displayName" : "Store State",
          "dynamic" : false,
          "identifiesControllerService" : false,
          "name" : "Store State",
          "sensitive" : false
        },
        "upload_api_url" : {
          "displayName" : "upload_api_url",
          "dynamic" : true,
          "identifiesControllerService" : false,
          "name" : "upload_api_url",
          "sensitive" : false
        },
        "Cache Value Lookup Cache Size" : {
          "displayName" : "Cache Value Lookup Cache Size",
          "dynamic" : false,
          "identifiesControllerService" : false,
          "name" : "Cache Value Lookup Cache Size",
          "sensitive" : false
        },
        "Stateful Variables Initial Value" : {
          "displayName" : "Stateful Variables Initial Value",
          "dynamic" : false,
          "identifiesControllerService" : false,
          "name" : "Stateful Variables Initial Value",
          "sensitive" : false
        },
        "multipart_field_name" : {
          "displayName" : "multipart_field_name",
          "dynamic" : true,
          "identifiesControllerService" : false,
          "name" : "multipart_field_name",
          "sensitive" : false
        }
      },
      "retriedRelationships" : [ ],
      "retryCount" : 10,
      "runDurationMillis" : 25,
      "scheduledState" : "ENABLED",
      "schedulingPeriod" : "0 sec",
      "schedulingStrategy" : "TIMER_DRIVEN",
      "style" : { },
      "type" : "org.apache.nifi.processors.attributes.UpdateAttribute",
      "yieldDuration" : "1 sec"
    }, {
      "autoTerminatedRelationships" : [ "success" ],
      "backoffMechanism" : "PENALIZE_FLOWFILE",
      "bulletinLevel" : "WARN",
      "bundle" : {
        "artifact" : "nifi-standard-nar",
        "group" : "org.apache.nifi",
        "version" : "2.10.0"
      },
      "comments" : "",
      "componentType" : "PROCESSOR",
      "concurrentlySchedulableTaskCount" : 1,
      "executionNode" : "ALL",
      "groupIdentifier" : "flow-contents-group",
      "identifier" : "f9202b45-38ba-36a5-b538-82d8b66a2d23",
      "maxBackoffPeriod" : "10 mins",
      "name" : "LogUploadResult",
      "penaltyDuration" : "30 sec",
      "position" : {
        "x" : 5312.0,
        "y" : 1152.0
      },
      "properties" : {
        "Log FlowFile Properties" : "true",
        "Log Level" : "info",
        "Attributes to Log" : "invokehttp.status.code,invokehttp.status.message",
        "Output Format" : "Line per Attribute",
        "Log Payload" : "false",
        "Character Set" : "UTF-8",
        "Attributes to Log Regular Expression" : "invokehttp\\.status\\..*"
      },
      "propertyDescriptors" : {
        "Log FlowFile Properties" : {
          "displayName" : "Log FlowFile Properties",
          "dynamic" : false,
          "identifiesControllerService" : false,
          "name" : "Log FlowFile Properties",
          "sensitive" : false
        },
        "Log Level" : {
          "displayName" : "Log Level",
          "dynamic" : false,
          "identifiesControllerService" : false,
          "name" : "Log Level",
          "sensitive" : false
        },
        "Attributes to Ignore" : {
          "displayName" : "Attributes to Ignore",
          "dynamic" : false,
          "identifiesControllerService" : false,
          "name" : "Attributes to Ignore",
          "sensitive" : false
        },
        "Attributes to Log" : {
          "displayName" : "Attributes to Log",
          "dynamic" : false,
          "identifiesControllerService" : false,
          "name" : "Attributes to Log",
          "sensitive" : false
        },
        "Attributes to Ignore Regular Expression" : {
          "displayName" : "Attributes to Ignore Regular Expression",
          "dynamic" : false,
          "identifiesControllerService" : false,
          "name" : "Attributes to Ignore Regular Expression",
          "sensitive" : false
        },
        "Output Format" : {
          "displayName" : "Output Format",
          "dynamic" : false,
          "identifiesControllerService" : false,
          "name" : "Output Format",
          "sensitive" : false
        },
        "Log Payload" : {
          "displayName" : "Log Payload",
          "dynamic" : false,
          "identifiesControllerService" : false,
          "name" : "Log Payload",
          "sensitive" : false
        },
        "Log Prefix" : {
          "displayName" : "Log Prefix",
          "dynamic" : false,
          "identifiesControllerService" : false,
          "name" : "Log Prefix",
          "sensitive" : false
        },
        "Character Set" : {
          "displayName" : "Character Set",
          "dynamic" : false,
          "identifiesControllerService" : false,
          "name" : "Character Set",
          "sensitive" : false
        },
        "Attributes to Log Regular Expression" : {
          "displayName" : "Attributes to Log Regular Expression",
          "dynamic" : false,
          "identifiesControllerService" : false,
          "name" : "Attributes to Log Regular Expression",
          "sensitive" : false
        }
      },
      "retriedRelationships" : [ ],
      "retryCount" : 10,
      "runDurationMillis" : 25,
      "scheduledState" : "ENABLED",
      "schedulingPeriod" : "0 sec",
      "schedulingStrategy" : "TIMER_DRIVEN",
      "style" : { },
      "type" : "org.apache.nifi.processors.standard.LogAttribute",
      "yieldDuration" : "1 sec"
    } ],
    "remoteProcessGroups" : [ ],
    "scheduledState" : "ENABLED",
    "statelessFlowTimeout" : "1 min"
  },
  "flowEncodingVersion" : "1.0",
  "latest" : false,
  "parameterContexts" : { },
  "parameterProviders" : { },
  "snapshotMetadata" : {
    "author" : "admin",
    "flowIdentifier" : "database-upload",
    "timestamp" : 1784788133736
  }
}